sleuren/__init__.py
sleuren/sleuren.py
sleuren/plugins/__init__.py
sleuren/plugins/apt-updates.py
sleuren/plugins/asterisk.py
sleuren/plugins/bitninja.py
sleuren/plugins/cloudlinux-dbgov.py
sleuren/plugins/cloudlinux.py
sleuren/plugins/cpanel.py
sleuren/plugins/cpu.py
sleuren/plugins/cpu_freq.py
sleuren/plugins/dirsize.py
sleuren/plugins/diskinodes.py
sleuren/plugins/diskstatus-nvme.py
sleuren/plugins/diskstatus.py
sleuren/plugins/diskusage.py
sleuren/plugins/docker.py
sleuren/plugins/dovecot.py
sleuren/plugins/elasticsearch.py
sleuren/plugins/exim.py
sleuren/plugins/gpu.py
sleuren/plugins/haproxy.py
sleuren/plugins/httpd.py
sleuren/plugins/iostat.py
sleuren/plugins/janus.py
sleuren/plugins/kamailio.py
sleuren/plugins/litespeed.py
sleuren/plugins/loadavg.py
sleuren/plugins/loggedin.py
sleuren/plugins/mailq.py
sleuren/plugins/mdstat.py
sleuren/plugins/megacli.py
sleuren/plugins/memcached.py
sleuren/plugins/memory.py
sleuren/plugins/minecraft.py
sleuren/plugins/mongodb.py
sleuren/plugins/mysql.py
sleuren/plugins/network.py
sleuren/plugins/nginx.py
sleuren/plugins/openvpn.py
sleuren/plugins/phpfpm.py
sleuren/plugins/ping.py
sleuren/plugins/plesk-cgroups.py
sleuren/plugins/plugins.py
sleuren/plugins/postfix.py
sleuren/plugins/powerdns.py
sleuren/plugins/process.py
sleuren/plugins/proftpd.py
sleuren/plugins/rabbitmq.py
sleuren/plugins/redis_stat.py
sleuren/plugins/sleeper.py
sleuren/plugins/swap.py
sleuren/plugins/system.py
sleuren/plugins/temp.py
sleuren/plugins/unbound.py
sleuren/plugins/vms.py
sleuren/plugins/wp-toolkit.py
sleuren/plugins/yum-updates.py
sleuren-1.0.8.data/data/share/doc/sleuren/LICENSE
sleuren-1.0.8.data/data/share/doc/sleuren/README.md
sleuren-1.0.8.data/data/share/doc/sleuren/sleuren.ini
sleuren-1.0.8.dist-info/LICENSE
sleuren-1.0.8.dist-info/METADATA
sleuren-1.0.8.dist-info/WHEEL
sleuren-1.0.8.dist-info/entry_points.txt
sleuren-1.0.8.dist-info/top_level.txt
sleuren-1.0.8.dist-info/RECORD
