Metadata-Version: 2.1
Name: sleuren
Version: 1.0.8
Summary: Server monitoring agent
Home-page: https://github.com/sleuren/agent
Author: sleuren
Author-email: hello@sleuren.com
Maintainer: sleuren
Maintainer-email: hello@sleuren.com
License: MIT
Keywords: sleuren monitoring agent
Classifier: Development Status :: 5 - Production/Stable
Classifier: Environment :: No Input/Output (Daemon)
Classifier: Intended Audience :: System Administrators
Classifier: License :: OSI Approved :: BSD License
Classifier: Natural Language :: English
Classifier: Operating System :: POSIX :: Linux
Classifier: Programming Language :: Python :: 2.7
Classifier: Programming Language :: Python :: 3.4
Classifier: Programming Language :: Python :: 3.5
Classifier: Programming Language :: Python :: 3.6
Classifier: Topic :: System :: Monitoring
License-File: LICENSE
Requires-Dist: psutil
Requires-Dist: netifaces
Requires-Dist: configparser
Requires-Dist: future
Requires-Dist: distro
